bandersnatch_safety_db/__init__.py
bandersnatch_safety_db/safety_db.py
bandersnatch_safety_db-0.1.122139.dist-info/LICENSE.txt
bandersnatch_safety_db-0.1.122139.dist-info/METADATA
bandersnatch_safety_db-0.1.122139.dist-info/RECORD
bandersnatch_safety_db-0.1.122139.dist-info/WHEEL
bandersnatch_safety_db-0.1.122139.dist-info/entry_points.txt
bandersnatch_safety_db-0.1.122139.dist-info/top_level.txt
bandersnatch_safety_db-0.1.122139.dist-info/zip-safe
