Metadata-Version: 2.1
Name: bandersnatch-safety-db
Version: 0.1.122139
Summary: Bandersnatch filtering plugin to filter packages listed in safety_db
Home-page: https://github.com/dwighthubbard/bandersnatch_safety_db
Author: Dwight Hubbard
Author-email: 254983+dwighthubbard@users.noreply.github.com
License: Academic Free License, version 3
Project-URL: Source, https://github.com/dwighthubbard/bandersnatch_safety_db
Keywords: bandersnatch python package mirror safety_db
Platform: UNKNOWN
Classifier: License :: OSI Approved :: Academic Free License (AFL)
Classifier: Programming Language :: Python :: 3 :: Only
Classifier: Programming Language :: Python :: 3.6
Classifier: Programming Language :: Python :: 3.7
Requires-Python: >=3.6
Provides-Extra: test
Provides-Extra: safety_package
Provides-Extra: doc_build
Requires-Dist: packaging
Requires-Dist: requests
Requires-Dist: bandersnatch (>3.3.0)
Requires-Dist: setuptools (>40.0.0)
Provides-Extra: doc_build
Requires-Dist: sphinx; extra == 'doc_build'
Requires-Dist: sphinx-bootstrap-theme; extra == 'doc_build'
Requires-Dist: guzzle-sphinx-theme; extra == 'doc_build'
Requires-Dist: sphinx-rtd-theme; extra == 'doc_build'
Requires-Dist: recommonmark; extra == 'doc_build'
Provides-Extra: safety_package
Requires-Dist: safety-db; extra == 'safety_package'
Provides-Extra: test
Requires-Dist: pytest; extra == 'test'
Requires-Dist: pytest-cov; extra == 'test'
Requires-Dist: vcrpy-unittest; extra == 'test'
